auto_dataclass/__init__.py
auto_dataclass/dj_model_to_dataclass.py
auto_dataclass/exceptions.py
auto_dataclass-0.1.6.dist-info/LICENSE
auto_dataclass-0.1.6.dist-info/WHEEL
auto_dataclass-0.1.6.dist-info/METADATA
auto_dataclass-0.1.6.dist-info/RECORD
