Metadata-Version: 2.1
Name: auto_dataclass
Version: 0.1.6
Summary: The package, helps to automatically transform data to DTO (DataClass) object
Author-email: Oleksandr Zhydyk <zhydykalex@ukr.net>
Classifier: License :: OSI Approved :: MIT License
Project-URL: Home, https://github.com/OleksandrZhydyk/Auto-Dataclass.git
